otp_yubikey/__init__.py
otp_yubikey/admin.py
otp_yubikey/apps.py
otp_yubikey/models.py
otp_yubikey/tests.py
otp_yubikey/migrations/0001_initial.py
otp_yubikey/migrations/0002_auto_20200723_1650.py
otp_yubikey/migrations/__init__.py
django_otp_yubikey-1.0.1.dist-info/LICENSE
django_otp_yubikey-1.0.1.dist-info/METADATA
django_otp_yubikey-1.0.1.dist-info/WHEEL
django_otp_yubikey-1.0.1.dist-info/top_level.txt
django_otp_yubikey-1.0.1.dist-info/RECORD
