Metadata-Version: 2.1
Name: django-otp-yubikey
Version: 1.0.1
Summary: A django-otp plugin that verifies YubiKey OTP tokens.
Home-page: https://github.com/django-otp/django-otp-yubikey
Author: Peter Sagerson
Author-email: psagers@ignorare.net
License: BSD
Project-URL: Documentation, https://django-otp-yubikey.readthedocs.io/
Project-URL: Source, https://github.com/django-otp/django-otp-yubikey
Platform: UNKNOWN
Classifier: Development Status :: 5 - Production/Stable
Classifier: Programming Language :: Python :: 3
Classifier: Programming Language :: Python :: 3 :: Only
Classifier: Intended Audience :: Developers
Classifier: License :: OSI Approved :: BSD License
Classifier: Topic :: Security
Classifier: Topic :: Software Development :: Libraries :: Python Modules
Classifier: Framework :: Django
License-File: LICENSE
